nectarifere/__init__.py
nectarifere/extracteur.py
nectarifere/falzar.py
nectarifere/nectar.py
nectarifere/Pictures/Echec/luc.jpg
nectarifere/Pictures/Echec/mickael.jpg
nectarifere/Pictures/Echec/oh_no_cringe.jpg
nectarifere/Pictures/Echec/shrek.jpg
nectarifere/Pictures/Echec/task.jpg
nectarifere/Pictures/Succes/confused.jpg
nectarifere/Pictures/Succes/hubert.jpg
nectarifere/Pictures/Succes/outofline.jpg
nectarifere/Pictures/Succes/samarch.jpg
nectarifere/Sounds/Kaamelott/Echec/file_0.wav
nectarifere/Sounds/Kaamelott/Echec/file_1.wav
nectarifere/Sounds/Kaamelott/Echec/file_10.wav
nectarifere/Sounds/Kaamelott/Echec/file_11.wav
nectarifere/Sounds/Kaamelott/Echec/file_12.wav
nectarifere/Sounds/Kaamelott/Echec/file_13.wav
nectarifere/Sounds/Kaamelott/Echec/file_14.wav
nectarifere/Sounds/Kaamelott/Echec/file_15.wav
nectarifere/Sounds/Kaamelott/Echec/file_16.wav
nectarifere/Sounds/Kaamelott/Echec/file_17.wav
nectarifere/Sounds/Kaamelott/Echec/file_18.wav
nectarifere/Sounds/Kaamelott/Echec/file_19.wav
nectarifere/Sounds/Kaamelott/Echec/file_2.wav
nectarifere/Sounds/Kaamelott/Echec/file_20.wav
nectarifere/Sounds/Kaamelott/Echec/file_21.wav
nectarifere/Sounds/Kaamelott/Echec/file_22.wav
nectarifere/Sounds/Kaamelott/Echec/file_23.wav
nectarifere/Sounds/Kaamelott/Echec/file_24.wav
nectarifere/Sounds/Kaamelott/Echec/file_25.wav
nectarifere/Sounds/Kaamelott/Echec/file_26.wav
nectarifere/Sounds/Kaamelott/Echec/file_27.wav
nectarifere/Sounds/Kaamelott/Echec/file_28.wav
nectarifere/Sounds/Kaamelott/Echec/file_29.wav
nectarifere/Sounds/Kaamelott/Echec/file_3.wav
nectarifere/Sounds/Kaamelott/Echec/file_30.wav
nectarifere/Sounds/Kaamelott/Echec/file_31.wav
nectarifere/Sounds/Kaamelott/Echec/file_32.wav
nectarifere/Sounds/Kaamelott/Echec/file_33.wav
nectarifere/Sounds/Kaamelott/Echec/file_34.wav
nectarifere/Sounds/Kaamelott/Echec/file_35.wav
nectarifere/Sounds/Kaamelott/Echec/file_36.wav
nectarifere/Sounds/Kaamelott/Echec/file_37.wav
nectarifere/Sounds/Kaamelott/Echec/file_38.wav
nectarifere-2.4.dist-info/LICENSE
nectarifere-2.4.dist-info/METADATA
nectarifere-2.4.dist-info/WHEEL
nectarifere-2.4.dist-info/top_level.txt
nectarifere-2.4.dist-info/RECORD
