Metadata-Version: 2.1
Name: nectarifere
Version: 2.4
Summary: Décorateur pour ambiancer vos codes.
Home-page: https://github.com/XanAstia/Nectarifere.git
Author: Xan Astia
Author-email: xan.astia@live.fr
License: MIT
License-File: LICENSE
Requires-Dist: play-sounds
Requires-Dist: playsound (==1.2.2)
Requires-Dist: pillow
